{
  "id": "e9d9b341-0c7a-4e9e-a9c4-12fd3f4bd37b",
  "prevId": "00000000-0000-0000-0000-000000000000",
  "version": "7",
  "dialect": "postgresql",
  "tables": {
    "public.items": {
      "name": "items",
      "schema": "",
      "columns": {
        "id": {
          "name": "id",
          "type": "bigserial",
          "primaryKey": true,
          "notNull": true
        },
        "market_hash_name": {
          "name": "market_hash_name",
          "type": "varchar(255)",
          "primaryKey": false,
          "notNull": true
        },
        "steam_appid": {
          "name": "steam_appid",
          "type": "integer",
          "primaryKey": false,
          "notNull": true
        },
        "created_at": {
          "name": "created_at",
          "type": "timestamp with time zone",
          "primaryKey": false,
          "notNull": true,
          "default": "now()"
        }
      },
      "indexes": {
        "market_hash_name_idx": {
          "name": "market_hash_name_idx",
          "columns": [
            {
              "expression": "market_hash_name",
              "isExpression": false,
              "asc": true,
              "nulls": "last"
            }
          ],
          "isUnique": false,
          "concurrently": false,
          "method": "btree",
          "with": {}
        }
      },
      "foreignKeys": {},
      "compositePrimaryKeys": {},
      "uniqueConstraints": {
        "items_market_hash_name_unique": {
          "name": "items_market_hash_name_unique",
          "nullsNotDistinct": false,
          "columns": [
            "market_hash_name"
          ]
        }
      },
      "policies": {},
      "checkConstraints": {},
      "isRLSEnabled": false
    },
    "public.price_history": {
      "name": "price_history",
      "schema": "",
      "columns": {
        "id": {
          "name": "id",
          "type": "bigserial",
          "primaryKey": true,
          "notNull": true
        },
        "item_id": {
          "name": "item_id",
          "type": "bigint",
          "primaryKey": false,
          "notNull": true
        },
        "price": {
          "name": "price",
          "type": "double precision",
          "primaryKey": false,
          "notNull": true
        },
        "recorded_at": {
          "name": "recorded_at",
          "type": "timestamp with time zone",
          "primaryKey": false,
          "notNull": true,
          "default": "now()"
        }
      },
      "indexes": {
        "item_id_idx": {
          "name": "item_id_idx",
          "columns": [
            {
              "expression": "item_id",
              "isExpression": false,
              "asc": true,
              "nulls": "last"
            }
          ],
          "isUnique": false,
          "concurrently": false,
          "method": "btree",
          "with": {}
        },
        "recorded_at_idx": {
          "name": "recorded_at_idx",
          "columns": [
            {
              "expression": "recorded_at",
              "isExpression": false,
              "asc": true,
              "nulls": "last"
            }
          ],
          "isUnique": false,
          "concurrently": false,
          "method": "btree",
          "with": {}
        },
        "item_id_recorded_at_idx": {
          "name": "item_id_recorded_at_idx",
          "columns": [
            {
              "expression": "item_id",
              "isExpression": false,
              "asc": true,
              "nulls": "last"
            },
            {
              "expression": "recorded_at",
              "isExpression": false,
              "asc": true,
              "nulls": "last"
            }
          ],
          "isUnique": false,
          "concurrently": false,
          "method": "btree",
          "with": {}
        }
      },
      "foreignKeys": {
        "price_history_item_id_items_id_fk": {
          "name": "price_history_item_id_items_id_fk",
          "tableFrom": "price_history",
          "tableTo": "items",
          "columnsFrom": [
            "item_id"
          ],
          "columnsTo": [
            "id"
          ],
          "onDelete": "cascade",
          "onUpdate": "no action"
        }
      },
      "compositePrimaryKeys": {},
      "uniqueConstraints": {},
      "policies": {},
      "checkConstraints": {},
      "isRLSEnabled": false
    }
  },
  "enums": {},
  "schemas": {},
  "sequences": {},
  "roles": {},
  "policies": {},
  "views": {},
  "_meta": {
    "columns": {},
    "schemas": {},
    "tables": {}
  }
}